google/cloud/geminidataanalytics/__init__.py
google/cloud/geminidataanalytics/gapic_version.py
google/cloud/geminidataanalytics/py.typed
google/cloud/geminidataanalytics_v1alpha/__init__.py
google/cloud/geminidataanalytics_v1alpha/gapic_metadata.json
google/cloud/geminidataanalytics_v1alpha/gapic_version.py
google/cloud/geminidataanalytics_v1alpha/py.typed
google/cloud/geminidataanalytics_v1alpha/services/__init__.py
google/cloud/geminidataanalytics_v1alpha/services/data_agent_service/__init__.py
google/cloud/geminidataanalytics_v1alpha/services/data_agent_service/async_client.py
google/cloud/geminidataanalytics_v1alpha/services/data_agent_service/client.py
google/cloud/geminidataanalytics_v1alpha/services/data_agent_service/pagers.py
google/cloud/geminidataanalytics_v1alpha/services/data_agent_service/transports/__init__.py
google/cloud/geminidataanalytics_v1alpha/services/data_agent_service/transports/base.py
google/cloud/geminidataanalytics_v1alpha/services/data_agent_service/transports/grpc.py
google/cloud/geminidataanalytics_v1alpha/services/data_agent_service/transports/grpc_asyncio.py
google/cloud/geminidataanalytics_v1alpha/services/data_agent_service/transports/rest.py
google/cloud/geminidataanalytics_v1alpha/services/data_agent_service/transports/rest_base.py
google/cloud/geminidataanalytics_v1alpha/services/data_chat_service/__init__.py
google/cloud/geminidataanalytics_v1alpha/services/data_chat_service/async_client.py
google/cloud/geminidataanalytics_v1alpha/services/data_chat_service/client.py
google/cloud/geminidataanalytics_v1alpha/services/data_chat_service/pagers.py
google/cloud/geminidataanalytics_v1alpha/services/data_chat_service/transports/__init__.py
google/cloud/geminidataanalytics_v1alpha/services/data_chat_service/transports/base.py
google/cloud/geminidataanalytics_v1alpha/services/data_chat_service/transports/grpc.py
google/cloud/geminidataanalytics_v1alpha/services/data_chat_service/transports/grpc_asyncio.py
google_cloud_geminidataanalytics-0.9.0.dist-info/licenses/LICENSE
google_cloud_geminidataanalytics-0.9.0.dist-info/METADATA
google_cloud_geminidataanalytics-0.9.0.dist-info/WHEEL
google_cloud_geminidataanalytics-0.9.0.dist-info/top_level.txt
google_cloud_geminidataanalytics-0.9.0.dist-info/RECORD
